aiohttp_retry/__init__.py
aiohttp_retry/client.py
aiohttp_retry/py.typed
aiohttp_retry/retry_options.py
aiohttp_retry/types.py
aiohttp_retry-2.9.0.dist-info/AUTHORS
aiohttp_retry-2.9.0.dist-info/LICENSE
aiohttp_retry-2.9.0.dist-info/METADATA
aiohttp_retry-2.9.0.dist-info/WHEEL
aiohttp_retry-2.9.0.dist-info/top_level.txt
aiohttp_retry-2.9.0.dist-info/RECORD
