Metadata-Version: 2.1
Name: aiohttp-retry
Version: 2.9.0
Summary: Simple retry client for aiohttp
Home-page: https://github.com/inyutin/aiohttp_retry
Author: Dmitry Inyutin
Author-email: inyutin.da@gmail.com
License: MIT
Keywords: aiohttp retry client
Platform: any
Classifier: Programming Language :: Python :: 3
Classifier: License :: OSI Approved :: MIT License
Classifier: Operating System :: OS Independent
Requires-Python: >=3.7
License-File: LICENSE
License-File: AUTHORS
